tkc/__init__.py
tkc/cli.py
tkc/lib.py
tkc-0.1.1.dist-info/METADATA
tkc-0.1.1.dist-info/WHEEL
tkc-0.1.1.dist-info/entry_points.txt
tkc-0.1.1.dist-info/licenses/LICENSE
tkc-0.1.1.dist-info/RECORD
