Metadata-Version: 2.3
Name: tkc
Version: 0.1.1
Summary: wc for tokens
Project-URL: Homepage, https://github.com/abizer/tkc
Project-URL: Issues, https://github.com/abizer/tkc/issues
Author-email: Abizer Lokhandwala <abizer@abizer.me>
Classifier: License :: OSI Approved :: MIT License
Classifier: Operating System :: OS Independent
Classifier: Programming Language :: Python :: 3
Requires-Python: >=3.12
Requires-Dist: anthropic>=0.40.0
Requires-Dist: litellm>=1.53.3
Requires-Dist: tabulate>=0.9.0
Requires-Dist: transformers>=4.46.3
